<?xml version="1.0" encoding="UTF-8"?>
<objects serializationModel="Studio.02.03.00">
	<object class="AudioFile" id="{5979b32d-a73e-4a99-9371-2a1be0aaffe6}">
		<property name="assetPath">
			<value>WAV/Modern2.wav</value>
		</property>
		<property name="frequencyInKHz">
			<value>44.0999985</value>
		</property>
		<property name="channelCount">
			<value>2</value>
		</property>
		<property name="length">
			<value>0.71251700680272112</value>
		</property>
		<relationship name="masterAssetFolder">
			<destination>{d29ea9f0-0852-4848-be31-5eae5f49058c}</destination>
		</relationship>
	</object>
</objects>
